README
setup.cfg
setup.py
ndg/__init__.py
ndg/oauth/__init__.py
ndg/oauth/server/__init__.py
ndg/oauth/server/examples/__init__.py
ndg/oauth/server/examples/utils.py
ndg/oauth/server/examples/bearer_tok/__init__.py
ndg/oauth/server/examples/bearer_tok/bearer_tok_server_app.ini
ndg/oauth/server/examples/bearer_tok/bearer_tok_server_app_serve.py
ndg/oauth/server/examples/bearer_tok/client_register.ini
ndg/oauth/server/examples/bearer_tok/passwd
ndg/oauth/server/examples/bearer_tok/repoze_who.ini
ndg/oauth/server/examples/bearer_tok/static/__init__.py
ndg/oauth/server/examples/bearer_tok/static/layout/CEDA_RightButton60.png
ndg/oauth/server/examples/bearer_tok/static/layout/__init__.py
ndg/oauth/server/examples/bearer_tok/static/layout/default.css
ndg/oauth/server/examples/bearer_tok/static/layout/help.png
ndg/oauth/server/examples/bearer_tok/templates/__init__.py
ndg/oauth/server/examples/bearer_tok/templates/auth_client_form.html
ndg/oauth/server/examples/bearer_tok/templates/base.html
ndg/oauth/server/examples/bearer_tok/templates/login_cancelled.html
ndg/oauth/server/examples/bearer_tok/templates/login_form.html
ndg/oauth/server/examples/shared_config/__init__.py
ndg/oauth/server/examples/shared_config/pki/__init__.py
ndg/oauth/server/examples/shared_config/pki/localhost.pem
ndg/oauth/server/examples/shared_config/pki/ca/08bd99c7.0
ndg/oauth/server/examples/shared_config/pki/ca/__init__.py
ndg/oauth/server/examples/shared_config/pki/ca/ade0138a.0
ndg/oauth/server/examples/slcs/README
ndg/oauth/server/examples/slcs/__init__.py
ndg/oauth/server/examples/slcs/client_register.ini
ndg/oauth/server/examples/slcs/passwd
ndg/oauth/server/examples/slcs/repoze_who.ini
ndg/oauth/server/examples/slcs/slcs_server_app.ini
ndg/oauth/server/examples/slcs/slcs_server_app_serve.py
ndg/oauth/server/examples/slcs/static/__init__.py
ndg/oauth/server/examples/slcs/static/layout/CEDA_RightButton60.png
ndg/oauth/server/examples/slcs/static/layout/__init__.py
ndg_oauth_server.egg-info/PKG-INFO
ndg_oauth_server.egg-info/SOURCES.txt
ndg_oauth_server.egg-info/dependency_links.txt
ndg_oauth_server.egg-info/not-zip-safe
ndg_oauth_server.egg-info/requires.txt
ndg_oauth_server.egg-info/top_level.txt