Metadata-Version: 1.1
Name: ndg-oauth-server
Version: 0.6.0
Summary: OAuth 2.0 server
Home-page: https://github.com/cedadev/ndg_oauth/
Author: Philip Kershaw
Author-email: Philip.Kershaw@stfc.ac.uk
License: BSD - See LICENCE file for details
Platform: UNKNOWN
Classifier: Development Status :: 3 - Alpha
Classifier: Environment :: Console
Classifier: Environment :: Web Environment
Classifier: Intended Audience :: End Users/Desktop
Classifier: Intended Audience :: Developers
Classifier: Intended Audience :: System Administrators
Classifier: Intended Audience :: Science/Research
Classifier: License :: OSI Approved :: BSD License
Classifier: Natural Language :: English
Classifier: Operating System :: Microsoft :: Windows
Classifier: Operating System :: POSIX :: Linux
Classifier: Programming Language :: Python
Classifier: Topic :: Security
Classifier: Topic :: Internet
Classifier: Topic :: Scientific/Engineering
Classifier: Topic :: System :: Distributed Computing
Classifier: Topic :: System :: Systems Administration :: Authentication/Directory
Classifier: Topic :: Software Development :: Libraries :: Python Modules
